file_organizer_tool/__init__.py
file_organizer_tool/config.py
file_organizer_tool/models.py
file_organizer_tool/organizer.py
file_organizer_tool/undo.py
file_organizer_tool-2.0.0.dist-info/METADATA
file_organizer_tool-2.0.0.dist-info/WHEEL
file_organizer_tool-2.0.0.dist-info/entry_points.txt
file_organizer_tool-2.0.0.dist-info/licenses/LICENSE
file_organizer_tool-2.0.0.dist-info/RECORD
