Metadata-Version: 2.4
Name: file-organizer-tool
Version: 2.0.0
Summary: A powerful tool to organize files in directories based on their extensions.
Project-URL: Homepage, https://github.com/albizzy/file_organizer
Project-URL: Repository, https://github.com/albizzy/file_organizer
Project-URL: Issues, https://github.com/albizzy/file_organizer/issues
Author-email: Albert Mwasisoba <almwassy@gmail.com>
License-Expression: MIT
License-File: LICENSE
Keywords: automation,cli,directory,file,organizer
Classifier: Development Status :: 4 - Beta
Classifier: Environment :: Console
Classifier: Intended Audience :: Developers
Classifier: Intended Audience :: End Users/Desktop
Classifier: License :: OSI Approved :: MIT License
Classifier: Operating System :: OS Independent
Classifier: Programming Language :: Python :: 3
Classifier: Programming Language :: Python :: 3.10
Classifier: Programming Language :: Python :: 3.11
Classifier: Programming Language :: Python :: 3.12
Classifier: Topic :: Desktop Environment :: File Managers
Classifier: Topic :: System :: Filesystems
Classifier: Topic :: Utilities
Requires-Python: >=3.10
Provides-Extra: all
Requires-Dist: pyyaml>=6.0; extra == 'all'
Requires-Dist: watchdog>=3.0; extra == 'all'
Provides-Extra: dev
Requires-Dist: pytest-cov>=4.0; extra == 'dev'
Requires-Dist: pytest>=7.0; extra == 'dev'
Requires-Dist: pyyaml>=6.0; extra == 'dev'
Provides-Extra: watch
Requires-Dist: watchdog>=3.0; extra == 'watch'
Provides-Extra: yaml
Requires-Dist: pyyaml>=6.0; extra == 'yaml'
